pygon/__init__.py
pygon/__main__.py
pygon/abc.py
pygon/activity.py
pygon/appinfo.py
pygon/asset.py
pygon/audit_logs.py
pygon/backoff.py
pygon/channel.py
pygon/client.py
pygon/colour.py
pygon/components.py
pygon/context_managers.py
pygon/embeds.py
pygon/emoji.py
pygon/enums.py
pygon/errors.py
pygon/file.py
pygon/flags.py
pygon/gateway.py
pygon/guild.py
pygon/http.py
pygon/integrations.py
pygon/interactions.py
pygon/invite.py
pygon/iterators.py
pygon/member.py
pygon/mentions.py
pygon/message.py
pygon/mixins.py
pygon/object.py
pygon/oggparse.py
pygon/opus.py
pygon/partial_emoji.py
pygon/permissions.py
pygon/player.py
pygon/py.typed
pygon/raw_models.py
pygon/reaction.py
pygon/role.py
pygon/shard.py
pygon/stage_instance.py
pygon/state.py
pygon/sticker.py
pygon/team.py
pygon/template.py
pygon/threads.py
pygon/user.py
pygon/utils.py
pygon/voice_client.py
pygon/widget.py
pygon/bin/libopus-0.x64.dll
pygon/bin/libopus-0.x86.dll
pygon/ext/commands/__init__.py
pygon/ext/commands/_types.py
pygon/ext/commands/bot.py
pygon/ext/commands/cog.py
pygon/ext/commands/context.py
pygon/ext/commands/converter.py
pygon/ext/commands/cooldowns.py
pygon/ext/commands/core.py
pygon/ext/commands/errors.py
pygon/ext/commands/flags.py
pygon/ext/commands/help.py
pygon/ext/commands/view.py
pygon/ext/tasks/__init__.py
pygon/types/__init__.py
pygon/types/activity.py
pygon/types/appinfo.py
pygon/types/audit_log.py
pygon/types/channel.py
pygon/types/components.py
pygon/types/embed.py
pygon/types/emoji.py
pygon/types/gateway.py
pygon/types/guild.py
pygon/types/integration.py
pygon/types/interactions.py
pygon/types/invite.py
pygon/types/member.py
pygon/types/message.py
pygon/types/raw_models.py
pygon/types/role.py
pygon/types/snowflake.py
pygon/types/sticker.py
pygon/types/team.py
pygon/types/template.py
pygon/types/threads.py
pygon/types/user.py
pygon/types/voice.py
pygon/types/webhook.py
pygon/types/welcome_screen.py
pygon/types/widget.py
pygon/ui/__init__.py
pygon/ui/button.py
pygon/ui/item.py
pygon-2.0.0a0.dist-info/LICENSE
pygon-2.0.0a0.dist-info/METADATA
pygon-2.0.0a0.dist-info/WHEEL
pygon-2.0.0a0.dist-info/top_level.txt
pygon-2.0.0a0.dist-info/RECORD
